{"config_hash":"sha256:b62b04ef69660b404b86899c80321f12170b35b287cabf0b60d05989a215f88b","no_leakage_statement":"no post-drift task rows were used for calibration","phase_scope":"phase_a_calibration_only","policy_by_family":{"code_transform":"receipt_template_only","json_schema_repair":"context_shortening_policy","obligation_closure":"context_shortening_policy","replay_rollback_receipt":"receipt_template_only","safe_python_expression":"context_shortening_policy","validator_receipt":"receipt_template_only"},"policy_catalog_hash":"sha256:d636da22af391c112e3f295d15ac409d3b3acb8e10320b0ddcf171c520951044","policy_hash":"sha256:6796373929cf65f41a0395e313e2973bae696cf61bf7df9bf882cc2b91acc5f8","receipt_type":"strong_baseline_calibration_receipt","status":"strong_baseline_calibrated","strong_static_debt_reduction_bps":7500,"strong_summary":{"active_mutation_count":0,"active_mutation_epoch_count":0,"active_mutation_ids":[],"attempts":16,"char_budget":3268,"closed":11,"closure_rate_bps":6875,"cost_to_close_units":27610,"evidence_gap":5,"hard_floor_regression_count":0,"latency_ms":83507,"operational_debt_auc":20,"parse_failures":0,"retries":0,"rollback_failures":0,"rollback_gap":0,"task_count":16,"unresolved_obligations":5,"validation_failures":5},"weak_summary":{"active_mutation_count":0,"active_mutation_epoch_count":0,"active_mutation_ids":[],"attempts":16,"char_budget":3878,"closed":0,"closure_rate_bps":0,"cost_to_close_units":52701,"evidence_gap":16,"hard_floor_regression_count":0,"latency_ms":328309,"operational_debt_auc":80,"parse_failures":16,"retries":0,"rollback_failures":0,"rollback_gap":0,"task_count":16,"unresolved_obligations":16,"validation_failures":16}}